larvaworld/__init__.py
larvaworld/cli/__init__.py
larvaworld/cli/argparser.py
larvaworld/cli/main.py
larvaworld/dashboards/__init__.py
larvaworld/dashboards/experiment_viewer.py
larvaworld/dashboards/lateral_oscillator_inspector.py
larvaworld/dashboards/main.py
larvaworld/dashboards/model_inspector.py
larvaworld/dashboards/module_inspector.py
larvaworld/dashboards/neural_oscillator_inspector.py
larvaworld/dashboards/track_viewer.py
larvaworld/data/SchleyerGroup/raw/exploration/dish01/10.csv
larvaworld/data/SchleyerGroup/raw/exploration/dish01/11.csv
larvaworld/data/SchleyerGroup/raw/exploration/dish01/12.csv
larvaworld/data/SchleyerGroup/raw/exploration/dish01/17.csv
larvaworld/data/SchleyerGroup/raw/exploration/dish01/18.csv
larvaworld/data/SchleyerGroup/raw/exploration/dish01/189.csv
larvaworld/data/SchleyerGroup/raw/exploration/dish01/3.csv
larvaworld/data/SchleyerGroup/raw/exploration/dish01/48.csv
larvaworld/data/SchleyerGroup/raw/exploration/dish01/49.csv
larvaworld/data/SchleyerGroup/raw/exploration/dish01/54.csv
larvaworld/data/SchleyerGroup/raw/exploration/dish01/55.csv
larvaworld/data/SchleyerGroup/raw/exploration/dish01/62.csv
larvaworld/data/SchleyerGroup/raw/exploration/dish01/63.csv
larvaworld/data/SchleyerGroup/raw/exploration/dish01/7.csv
larvaworld/data/SchleyerGroup/raw/exploration/dish01/71.csv
larvaworld/data/SchleyerGroup/raw/exploration/dish01/87.csv
larvaworld/data/SchleyerGroup/raw/exploration/dish01/9.csv
larvaworld/data/SchleyerGroup/raw/exploration/dish01/93.csv
larvaworld/data/SchleyerGroup/raw/exploration/dish02/10.csv
larvaworld/data/SchleyerGroup/raw/exploration/dish02/109.csv
larvaworld/data/SchleyerGroup/raw/exploration/dish02/11.csv
larvaworld/data/SchleyerGroup/raw/exploration/dish02/119.csv
larvaworld/data/SchleyerGroup/raw/exploration/dish02/122.csv
larvaworld/data/SchleyerGroup/raw/exploration/dish02/126.csv
larvaworld/data/SchleyerGroup/raw/exploration/dish02/148.csv
larvaworld/data/SchleyerGroup/raw/exploration/dish02/154.csv
larvaworld-2.1.0.dist-info/METADATA
larvaworld-2.1.0.dist-info/WHEEL
larvaworld-2.1.0.dist-info/entry_points.txt
larvaworld-2.1.0.dist-info/licenses/LICENSE
larvaworld-2.1.0.dist-info/RECORD
