Metadata-Version: 2.4
Name: larvaworld
Version: 2.1.0
Summary: A virtual lab for Drosophila larva behavioral modeling and analysis
License: MIT
License-File: LICENSE
Author: Panagiotis Sakagiannis
Author-email: bagjohn0@gmail.com
Requires-Python: >=3.10,<3.14
Classifier: Development Status :: 2 - Pre-Alpha
Classifier: Intended Audience :: Science/Research
Classifier: License :: OSI Approved :: MIT License
Classifier: Natural Language :: English
Classifier: Operating System :: OS Independent
Classifier: Programming Language :: Python :: 3
Classifier: Programming Language :: Python :: 3.10
Classifier: Programming Language :: Python :: 3.11
Classifier: Programming Language :: Python :: 3.12
Classifier: Programming Language :: Python :: 3.13
Classifier: Topic :: Software Development :: Libraries
Requires-Dist: SALib (<1.5.2)
Requires-Dist: agentpy (==0.1.*)
Requires-Dist: argparse (==1.4.*)
Requires-Dist: docopt (==0.6.*)
Requires-Dist: filelock (>=3.12.0,<4.0.0)
Requires-Dist: geopandas (>=0.13,<1.0)
Requires-Dist: holoviews (>=1.17,<2.0)
Requires-Dist: hvplot (>=0.10,<1.0)
Requires-Dist: imageio[ffmpeg] (>=2.35,<3.0)
Requires-Dist: matplotlib (>=3.7,<4.0)
Requires-Dist: movingpandas (>=0.19,<1.0)
Requires-Dist: numpy (>=1.24,<2.0)
Requires-Dist: pandas (>=2.0,<3.0)
Requires-Dist: panel (==1.2.*)
Requires-Dist: param (==2.1.*)
Requires-Dist: pint (>=0.21,<1.0)
Requires-Dist: pint_pandas (>=0.3,<1.0)
Requires-Dist: powerlaw (==1.5)
Requires-Dist: progressbar (==2.5)
Requires-Dist: pygame (>=2.6,<3.0)
Requires-Dist: pypdf (>=5.0,<6.0)
Requires-Dist: rich (>=10)
Requires-Dist: scikit-learn (>=1.3,<2.0)
Requires-Dist: scipy (>=1.9,<2.0)
Requires-Dist: seaborn (>=0.13,<1.0)
Requires-Dist: shapely (>=2.0,<3.0)
Requires-Dist: statannot (==0.2.*)
Requires-Dist: tables (>=3.9.0,<4.0.0)
Requires-Dist: typer[all] (>=0.9.0,<0.10.0)
Requires-Dist: typing-extensions (>=4.12,<5.0)
Project-URL: Bug Tracker, https://github.com/nawrotlab/larvaworld/issues
Project-URL: Changelog, https://github.com/nawrotlab/larvaworld/blob/main/CHANGELOG.md
Project-URL: Documentation, https://larvaworld.readthedocs.io
Project-URL: Repository, https://github.com/nawrotlab/larvaworld
